{
  "main": {
    "id": "3bc4b8695283497e",
    "type": "split",
    "children": [
      {
        "id": "6532cf5b3b963866",
        "type": "tabs",
        "children": [
          {
            "id": "daa358a9378fa458",
            "type": "leaf",
            "state": {
              "type": "markdown",
              "state": {
                "file": "Notes/高等代数-丘维声/L03 第三章 线性空间.md",
                "mode": "source",
                "source": false
              }
            }
          },
          {
            "id": "2c1bec2de5ffe803",
            "type": "leaf",
            "state": {
              "type": "markdown",
              "state": {
                "file": "References/Realtime Collision Detection.md",
                "mode": "source",
                "source": false
              }
            }
          },
          {
            "id": "903f8d605dd4d771",
            "type": "leaf",
            "state": {
              "type": "markdown",
              "state": {
                "file": "References/Collision Detection in Interactive 3D Environments.md",
                "mode": "source",
                "source": false
              }
            }
          }
        ],
        "currentTab": 2
      }
    ],
    "direction": "vertical"
  },
  "left": {
    "id": "5ce4feaed1be121e",
    "type": "split",
    "children": [
      {
        "id": "5bb815d9dbbf3283",
        "type": "tabs",
        "children": [
          {
            "id": "0791f6b4d3cc798b",
            "type": "leaf",
            "state": {
              "type": "file-explorer",
              "state": {
                "sortOrder": "alphabetical"
              }
            }
          },
          {
            "id": "4888b49fcd764482",
            "type": "leaf",
            "state": {
              "type": "search",
              "state": {
                "query": "",
                "matchingCase": false,
                "explainSearch": false,
                "collapseAll": false,
                "extraContext": false,
                "sortOrder": "alphabetical"
              }
            }
          },
          {
            "id": "e4ad4d99b186e447",
            "type": "leaf",
            "state": {
              "type": "starred",
              "state": {}
            }
          }
        ]
      }
    ],
    "direction": "horizontal",
    "width": 200
  },
  "right": {
    "id": "72f8acf711ad2196",
    "type": "split",
    "children": [
      {
        "id": "cb90cf4c374439cb",
        "type": "tabs",
        "children": [
          {
            "id": "5345c5af6e15536e",
            "type": "leaf",
            "state": {
              "type": "backlink",
              "state": {
                "file": "References/Collision Detection in Interactive 3D Environments.md",
                "collapseAll": false,
                "extraContext": false,
                "sortOrder": "alphabetical",
                "showSearch": false,
                "searchQuery": "",
                "backlinkCollapsed": false,
                "unlinkedCollapsed": true
              }
            }
          },
          {
            "id": "f47f9280116e6538",
            "type": "leaf",
            "state": {
              "type": "outgoing-link",
              "state": {
                "file": "References/Collision Detection in Interactive 3D Environments.md",
                "linksCollapsed": false,
                "unlinkedCollapsed": true
              }
            }
          },
          {
            "id": "8c0f3bd3e9117930",
            "type": "leaf",
            "state": {
              "type": "tag",
              "state": {
                "sortOrder": "frequency",
                "useHierarchy": true
              }
            }
          },
          {
            "id": "2280afd86cf40813",
            "type": "leaf",
            "state": {
              "type": "outline",
              "state": {
                "file": "References/Collision Detection in Interactive 3D Environments.md"
              }
            }
          }
        ]
      }
    ],
    "direction": "horizontal",
    "width": 300,
    "collapsed": true
  },
  "active": "903f8d605dd4d771",
  "lastOpenFiles": [
    "References/GOAP.md",
    "References/MIT 微积分重点.md",
    "References/Realtime Collision Detection.md",
    "References/What’s LLVM.md",
    "References/Collision Detection in Interactive 3D Environments.md",
    "Notes/高等代数-丘维声/L03 第三章 线性空间.md",
    "Notes/高等代数-丘维声/L02 第二章 N阶行列式.md",
    "Notes/Markdown中的数学公式.md",
    "Notes/高等代数-丘维声/L01 第一章 线性方程组的解法.md",
    "Notes/高等代数-丘维声/L00 引言：高等代数研究对象.md"
  ]
}